mechanex/__init__.py
mechanex/attribution.py
mechanex/base.py
mechanex/cli.py
mechanex/client.py
mechanex/errors.py
mechanex/generation.py
mechanex/model.py
mechanex/raag.py
mechanex/sae.py
mechanex/serving.py
mechanex/steering.py
mechanex/utils/__init__.py
mechanex/utils/steering_opt.py
mechanex-0.5.0.dist-info/licenses/LICENSE
mechanex-0.5.0.dist-info/METADATA
mechanex-0.5.0.dist-info/WHEEL
mechanex-0.5.0.dist-info/entry_points.txt
mechanex-0.5.0.dist-info/top_level.txt
mechanex-0.5.0.dist-info/RECORD
