Metadata-Version: 2.4
Name: mechanex
Version: 0.5.0
Summary: A Python client for the Axionic API.
Home-page: https://axioniclabs.ai
Author: Axionic Labs
Author-email: contact@axioniclabs.ai
Classifier: Programming Language :: Python :: 3
Classifier: License :: OSI Approved :: Apache Software License
Classifier: Operating System :: OS Independent
Requires-Python: >=3.7
License-File: LICENSE
Requires-Dist: requests>=2.20.0
Requires-Dist: ipython
Requires-Dist: jupyter
Requires-Dist: matplotlib
Requires-Dist: click
Requires-Dist: fastapi
Requires-Dist: uvicorn
Requires-Dist: torch
Requires-Dist: numpy
Requires-Dist: tqdm
Requires-Dist: mdmm
Requires-Dist: rich
Requires-Dist: sae-lens
Requires-Dist: openai
Requires-Dist: huggingface_hub
Dynamic: author
Dynamic: author-email
Dynamic: classifier
Dynamic: description
Dynamic: description-content-type
Dynamic: home-page
Dynamic: license-file
Dynamic: requires-dist
Dynamic: requires-python
Dynamic: summary
